{"assets/images/correo.png":["assets/images/correo.png"],"assets/images/correo_icon.png":["assets/images/correo_icon.png"],"assets/images/grafico_propuesta_valor.png":["assets/images/grafico_propuesta_valor.png"],"assets/images/logo_oceancomex.png":["assets/images/logo_oceancomex.png"],"assets/images/presentation_image.png":["assets/images/presentation_image.png"],"assets/images/propuesta_image.png":["assets/images/propuesta_image.png"],"assets/images/propuesta_image1.png":["assets/images/propuesta_image1.png"],"assets/images/quienessomosimg.png":["assets/images/quienessomosimg.png"],"assets/images/slider1.png":["assets/images/slider1.png"],"assets/images/slider2.png":["assets/images/slider2.png"],"assets/images/ubi.png":["assets/images/ubi.png"],"assets/images/ubicacion_icon.png":["assets/images/ubicacion_icon.png"],"assets/images/wpp.jpg":["assets/images/wpp.jpg"]}